aindex/__init__.py
aindex/aindex.py
aindex-0.1.1.dist-info/LICENSE
aindex-0.1.1.dist-info/METADATA
aindex-0.1.1.dist-info/WHEEL
aindex-0.1.1.dist-info/RECORD
