Metadata-Version: 2.1
Name: aindex
Version: 0.1.1
Summary: Reusable AI functions
License: MIT
Author: Eduardo Reis
Requires-Python: >=3.9,<4.0
Classifier: License :: OSI Approved :: MIT License
Classifier: Programming Language :: Python :: 3
Classifier: Programming Language :: Python :: 3.9
Classifier: Programming Language :: Python :: 3.10
Classifier: Programming Language :: Python :: 3.11
